scraper_itl/__init__.py
scraper_itl/controller.py
scraper_itl/itl.py
scraper_itl/ratelimited.py
scraper_itl-0.0.3.dist-info/METADATA
scraper_itl-0.0.3.dist-info/WHEEL
scraper_itl-0.0.3.dist-info/licenses/LICENSE
scraper_itl-0.0.3.dist-info/RECORD
